{
    "AX": {
        "error": 0.005766228959017357,
        "filter_outliers_dict": {
            "filter_outliers": true,
            "iterations": 1,
            "std_devs": 2,
            "use_iqr_filtering": false,
            "use_standard_deviation_filtering": false
        },
        "fit": "Average",
        "fn": 59,
        "include_baseline_error": false,
        "n": 60,
        "outlier_excluded": [
            5
        ],
        "reviewed": true,
        "user_excluded": [],
        "value": -0.07937722635392289
    },
    "CDD": {
        "error": 2.8342155984935655e-05,
        "filter_outliers_dict": {
            "filter_outliers": true,
            "iterations": 1,
            "std_devs": 10,
            "use_iqr_filtering": false,
            "use_standard_deviation_filtering": false
        },
        "fit": "Average",
        "fn": 60,
        "include_baseline_error": false,
        "n": 60,
        "outlier_excluded": [],
        "reviewed": true,
        "user_excluded": [],
        "value": 0.00035146169199530656
    },
    "H1": {
        "error": 0.005777985750178785,
        "filter_outliers_dict": {
            "filter_outliers": true,
            "iterations": 1,
            "std_devs": 2,
            "use_iqr_filtering": false,
            "use_standard_deviation_filtering": false
        },
        "fit": "Average",
        "fn": 57,
        "include_baseline_error": false,
        "n": 60,
        "outlier_excluded": [
            0,
            2,
            3
        ],
        "reviewed": true,
        "user_excluded": [],
        "value": 0.14459960476348274
    },
    "H2": {
        "error": 0.005951513615134475,
        "filter_outliers_dict": {
            "filter_outliers": true,
            "iterations": 1,
            "std_devs": 2
        },
        "fit": "average",
        "value": -0.22186718281547202
    },
    "L1": {
        "error": 0.0032066183353217847,
        "filter_outliers_dict": {
            "filter_outliers": true,
            "iterations": 1,
            "std_devs": 2,
            "use_iqr_filtering": false,
            "use_standard_deviation_filtering": false
        },
        "fit": "Average",
        "fn": 58,
        "include_baseline_error": false,
        "n": 60,
        "outlier_excluded": [
            1,
            4
        ],
        "reviewed": true,
        "user_excluded": [],
        "value": -0.032821128006366176
    },
    "L2": {
        "error": 0.006808210560226734,
        "filter_outliers_dict": {
            "filter_outliers": true,
            "iterations": 1,
            "std_devs": 2,
            "use_iqr_filtering": false,
            "use_standard_deviation_filtering": false
        },
        "fit": "Average",
        "fn": 58,
        "include_baseline_error": false,
        "n": 60,
        "outlier_excluded": [
            49,
            35
        ],
        "reviewed": true,
        "user_excluded": [],
        "value": -0.022875505515599047
    }
}