{
    "AX": {
        "error": 0.00751973840583656, 
        "filter_outliers_dict": {
            "filter_outliers": true, 
            "iterations": 1, 
            "std_devs": 2
        }, 
        "fit": "average", 
        "value": -0.06565318004287005
    }, 
    "CDD": {
        "error": 2.5908487230499693e-05, 
        "filter_outliers_dict": {
            "filter_outliers": true, 
            "iterations": 1, 
            "std_devs": 10
        }, 
        "fit": "average", 
        "value": 0.00036652433842544567
    }, 
    "H1": {
        "error": 0.006386764851756246, 
        "filter_outliers_dict": {
            "filter_outliers": true, 
            "iterations": 1, 
            "std_devs": 2
        }, 
        "fit": "average", 
        "value": 0.14453660436591292
    }, 
    "H2": {
        "error": 0.007682291289467511, 
        "filter_outliers_dict": {
            "filter_outliers": true, 
            "iterations": 1, 
            "std_devs": 2
        }, 
        "fit": "average", 
        "value": -0.202899657519758
    }, 
    "L1": {
        "error": 0.002990706899105019, 
        "filter_outliers_dict": {
            "filter_outliers": true, 
            "iterations": 1, 
            "std_devs": 2
        }, 
        "fit": "average", 
        "value": -0.03583501527407523
    }, 
    "L2": {
        "error": 0.0070033780508913564, 
        "filter_outliers_dict": {
            "filter_outliers": true, 
            "iterations": 1, 
            "std_devs": 2
        }, 
        "fit": "average", 
        "value": -0.024756013872571484
    }
}