{
    "AX": {
        "error": 0.00021105551918642433, 
        "fit": "Bracketing Interpolate", 
        "references": [
            {
                "exclude": "ok", 
                "record_id": "c-02-J-1662", 
                "uuid": "7da15e43-cac5-48f0-a878-828a4d627c72"
            }, 
            {
                "exclude": "ok", 
                "record_id": "c-02-J-1663", 
                "uuid": "b025ff9f-5aa9-448b-b00c-4b949835677a"
            }, 
            {
                "exclude": "ok", 
                "record_id": "c-02-J-1664", 
                "uuid": "d14116be-91b7-4cc8-90b3-da95a697b3f4"
            }, 
            {
                "exclude": "ok", 
                "record_id": "c-02-J-1665", 
                "uuid": "9ab3fbf8-8b62-4621-81c0-28b901d7a81b"
            }, 
            {
                "exclude": "ok", 
                "record_id": "c-02-J-1666", 
                "uuid": "ac0e3e01-5fa5-42b5-80fe-1ed06e3b85b2"
            }, 
            {
                "exclude": "ok", 
                "record_id": "c-02-J-1667", 
                "uuid": "4c9ae36b-c49b-4e6b-bdb1-39d09b8943c9"
            }, 
            {
                "exclude": "ok", 
                "record_id": "c-02-J-1668", 
                "uuid": "d7d38d43-675e-4a5c-b21a-062364021f21"
            }, 
            {
                "exclude": "ok", 
                "record_id": "c-02-J-1669", 
                "uuid": "18a00a4a-9981-48cf-b0a6-fa4caf718dd1"
            }, 
            {
                "exclude": "ok", 
                "record_id": "c-02-J-1670", 
                "uuid": "d7204503-d611-45fc-ac71-b155f63a7d0b"
            }, 
            {
                "exclude": "ok", 
                "record_id": "c-02-J-1671", 
                "uuid": "89edfa9f-ce74-4bdb-9f89-8ba8f5773848"
            }, 
            {
                "exclude": "ok", 
                "record_id": "c-02-J-1672", 
                "uuid": "30ff1441-0551-448b-b084-ca3872b185c7"
            }, 
            {
                "exclude": "ok", 
                "record_id": "c-02-J-1673", 
                "uuid": "7a1221af-2f36-4200-83c0-d087b7e37f78"
            }, 
            {
                "exclude": "ok", 
                "record_id": "c-02-J-1674", 
                "uuid": "f1889ee6-f71c-43f5-9bac-9d7be170f9a1"
            }, 
            {
                "exclude": "ok", 
                "record_id": "c-02-J-1675", 
                "uuid": "32cdb252-22c0-4201-8ccd-cac5072605a1"
            }, 
            {
                "exclude": "ok", 
                "record_id": "c-02-J-1676", 
                "uuid": "767a4f77-8661-4092-af94-634ad217efea"
            }, 
            {
                "exclude": "ok", 
                "record_id": "c-02-J-1677", 
                "uuid": "a56cc468-f1a7-49a5-b35e-a42b6b346873"
            }, 
            {
                "exclude": "ok", 
                "record_id": "c-02-J-1678", 
                "uuid": "a1bae3c6-441f-48ce-80cc-ba224b5eb6ba"
            }, 
            {
                "exclude": "ok", 
                "record_id": "c-02-J-1679", 
                "uuid": "61e6283d-a8e8-4a93-8a4b-923c2a8c8ec0"
            }, 
            {
                "exclude": "ok", 
                "record_id": "c-02-J-1680", 
                "uuid": "01939f2d-e9cb-45c1-80f6-146d83f2fd63"
            }, 
            {
                "exclude": "ok", 
                "record_id": "c-02-J-1681", 
                "uuid": "0f27c503-9083-496f-8dcf-84c602532687"
            }, 
            {
                "exclude": "ok", 
                "record_id": "c-02-J-1682", 
                "uuid": "e54a22fe-755c-4595-addb-db9b7c643c94"
            }, 
            {
                "exclude": "ok", 
                "record_id": "c-02-J-1683", 
                "uuid": "849ffe1a-0248-4045-969e-268a7b0228d6"
            }, 
            {
                "exclude": "ok", 
                "record_id": "c-02-J-1684", 
                "uuid": "da5ec0df-8fa3-4e7c-b264-20b1fbfd9c21"
            }, 
            {
                "exclude": "ok", 
                "record_id": "c-02-J-1685", 
                "uuid": "b93ad404-6ee3-4563-88fa-f72c94b8f780"
            }, 
            {
                "exclude": "ok", 
                "record_id": "c-02-J-1686", 
                "uuid": "eb1cb5cd-4e92-4e10-9f75-b0498bf0054a"
            }, 
            {
                "exclude": "ok", 
                "record_id": "c-02-J-1687", 
                "uuid": "4d32c2cb-486a-4f24-bbcf-84e5d8369680"
            }, 
            {
                "exclude": "ok", 
                "record_id": "c-02-J-1688", 
                "uuid": "b5ce784c-b6f7-46a2-8674-b134bafd3fc8"
            }, 
            {
                "exclude": "ok", 
                "record_id": "c-02-J-1689", 
                "uuid": "183aac0e-689d-445a-b276-bf8a3f7cfa9a"
            }, 
            {
                "exclude": "ok", 
                "record_id": "c-02-J-1690", 
                "uuid": "98779856-1bfc-4794-a1ef-1915ee1b2baa"
            }, 
            {
                "exclude": "ok", 
                "record_id": "c-02-J-1691", 
                "uuid": "d6f88579-efc6-4cbb-9403-cec7695198ad"
            }, 
            {
                "exclude": "ok", 
                "record_id": "c-02-J-1692", 
                "uuid": "5ef4525d-d54a-4c26-b0a4-f3c5487ea090"
            }, 
            {
                "exclude": "ok", 
                "record_id": "c-02-J-1693", 
                "uuid": "24166b17-55ad-4953-a474-92ff988905a2"
            }, 
            {
                "exclude": "ok", 
                "record_id": "c-02-J-1694", 
                "uuid": "d22083f5-9d6e-4194-9fca-2dac96ddb599"
            }, 
            {
                "exclude": "ok", 
                "record_id": "c-02-J-1695", 
                "uuid": "0c5627d7-44f6-40c1-a986-fe97fe17838a"
            }, 
            {
                "exclude": "ok", 
                "record_id": "c-02-J-1696", 
                "uuid": "6a4a5db7-7a0f-44ca-93c6-313d34f08258"
            }, 
            {
                "exclude": "ok", 
                "record_id": "c-02-J-1697", 
                "uuid": "fc3f67c5-ea93-424d-a3e4-3d013751bbd8"
            }, 
            {
                "exclude": "ok", 
                "record_id": "c-02-J-1698", 
                "uuid": "6436cf56-7a89-45bb-83b8-e88d6301da3c"
            }, 
            {
                "exclude": "ok", 
                "record_id": "c-02-J-1699", 
                "uuid": "01569a8b-416d-4784-8f34-99ba6375ffdf"
            }, 
            {
                "exclude": "ok", 
                "record_id": "c-02-J-1700", 
                "uuid": "876c3dee-4f8d-4365-9eec-5a7b1d143667"
            }, 
            {
                "exclude": "ok", 
                "record_id": "c-02-J-1701", 
                "uuid": "6b7faa0d-af23-4439-9cfc-c20b00d004ef"
            }, 
            {
                "exclude": "ok", 
                "record_id": "c-02-J-1702", 
                "uuid": "6d7aa9a7-963e-4119-8d4f-be5a76f599ff"
            }, 
            {
                "exclude": "ok", 
                "record_id": "c-02-J-1703", 
                "uuid": "50654396-f9c1-4a8d-be9d-085bcde06ffd"
            }, 
            {
                "exclude": "ok", 
                "record_id": "c-02-J-1704", 
                "uuid": "10194144-1e34-43ad-a863-306b616f7db6"
            }, 
            {
                "exclude": "ok", 
                "record_id": "c-02-J-1705", 
                "uuid": "d715b144-59b7-4c72-9406-f1e1291db26c"
            }, 
            {
                "exclude": "ok", 
                "record_id": "c-02-J-1706", 
                "uuid": "070199d7-47b8-4a10-8a76-744ab383605b"
            }, 
            {
                "exclude": "ok", 
                "record_id": "c-02-J-1707", 
                "uuid": "891cc7cc-f688-496f-baa5-92b874636b4e"
            }, 
            {
                "exclude": "ok", 
                "record_id": "c-02-J-1708", 
                "uuid": "6bece729-7a51-4829-896e-d5668553ea62"
            }, 
            {
                "exclude": "ok", 
                "record_id": "c-02-J-1709", 
                "uuid": "c68a84ec-8366-41cc-86f0-b0e776a86243"
            }, 
            {
                "exclude": "ok", 
                "record_id": "c-02-J-1710", 
                "uuid": "f790d796-3eff-4db5-9071-a78f474ca29b"
            }, 
            {
                "exclude": "ok", 
                "record_id": "c-02-J-1711", 
                "uuid": "6e7d2ff5-fe68-457a-a628-4dca033b5d4f"
            }, 
            {
                "exclude": "ok", 
                "record_id": "c-02-J-1712", 
                "uuid": "b5388db9-c7fe-48de-902e-7f734e32cd02"
            }, 
            {
                "exclude": "ok", 
                "record_id": "c-02-J-1713", 
                "uuid": "87c6963d-3334-438c-a71f-24d71af07d30"
            }, 
            {
                "exclude": "ok", 
                "record_id": "c-02-J-1714", 
                "uuid": "60216ab1-4b48-44e8-8102-bc8e9e1d9870"
            }, 
            {
                "exclude": "ok", 
                "record_id": "c-02-J-1715", 
                "uuid": "2887800a-73b3-471a-bb1a-6bcbd84b39a8"
            }, 
            {
                "exclude": "ok", 
                "record_id": "c-02-J-1716", 
                "uuid": "df13b29d-0aad-416a-b5e9-54e7ed49acad"
            }, 
            {
                "exclude": "ok", 
                "record_id": "c-02-J-1717", 
                "uuid": "2362c7c0-654f-45ef-abf6-ea7b6de441d7"
            }, 
            {
                "exclude": "ok", 
                "record_id": "c-02-J-1718", 
                "uuid": "ed4f2791-9c6a-42b1-b79e-579f26eb6051"
            }, 
            {
                "exclude": "ok", 
                "record_id": "c-02-J-1719", 
                "uuid": "17ecfdbc-292b-44fe-afe2-d39f4bf8109c"
            }, 
            {
                "exclude": "ok", 
                "record_id": "c-02-J-1720", 
                "uuid": "a1ae2a09-5057-4cbc-a796-4566eea6f408"
            }
        ], 
        "value": 1.0005174472939538
    }, 
    "CDD": {
        "error": 0.0017980589900768874, 
        "fit": "Average", 
        "references": [
            {
                "exclude": "ok", 
                "record_id": "a-01-J-5542", 
                "uuid": "1a9d81cd-4eef-45c9-8bfb-4bd8fdd555ab"
            }, 
            {
                "exclude": "ok", 
                "record_id": "a-01-J-5543", 
                "uuid": "6f73ad63-195f-4126-951b-6bd671cc03b3"
            }, 
            {
                "exclude": "ok", 
                "record_id": "a-01-J-5544", 
                "uuid": "0e17b263-d964-4a26-af67-febb61b6de22"
            }, 
            {
                "exclude": "omit", 
                "record_id": "a-01-J-5545", 
                "uuid": "2b1f8a89-9cd1-4174-913d-ad1bdee4e5de"
            }, 
            {
                "exclude": "omit", 
                "record_id": "a-01-J-5546", 
                "uuid": "70e92674-6904-4a9f-b993-4e8b03231a04"
            }, 
            {
                "exclude": "ok", 
                "record_id": "a-01-J-5547", 
                "uuid": "3ff7df10-dc44-41ae-8f72-0145ee4be7d0"
            }, 
            {
                "exclude": "ok", 
                "record_id": "a-01-J-5548", 
                "uuid": "9df8ebbf-4465-4522-baad-84b4bed80d5b"
            }, 
            {
                "exclude": "ok", 
                "record_id": "a-01-J-5549", 
                "uuid": "f5587710-1d45-4204-a616-9bd6360b9a01"
            }, 
            {
                "exclude": "omit", 
                "record_id": "a-01-J-5550", 
                "uuid": "322e538e-85f9-4877-8ab3-cb0c5361b6cb"
            }, 
            {
                "exclude": "ok", 
                "record_id": "a-01-J-5551", 
                "uuid": "e9a90c93-7e5b-4ea0-9c30-11b86b02ba42"
            }, 
            {
                "exclude": "omit", 
                "record_id": "a-01-J-5552", 
                "uuid": "363b50e4-804c-4695-a216-14e73b0c80c8"
            }, 
            {
                "exclude": "omit", 
                "record_id": "a-01-J-5553", 
                "uuid": "aac2f3aa-15d2-4886-b7bb-78e47982280f"
            }, 
            {
                "exclude": "ok", 
                "record_id": "a-01-J-5554", 
                "uuid": "d6b89347-ec82-4c58-855f-c9e10e381b04"
            }, 
            {
                "exclude": "omit", 
                "record_id": "a-01-J-5555", 
                "uuid": "bc4b66d1-7f3c-4f2b-9b34-a29af6327e57"
            }, 
            {
                "exclude": "ok", 
                "record_id": "a-01-J-5556", 
                "uuid": "8b1c6e60-3b26-45f5-8dcb-b493a6b8689d"
            }, 
            {
                "exclude": "ok", 
                "record_id": "a-01-J-5557", 
                "uuid": "e342eccf-29d8-419e-828b-52a23b341059"
            }, 
            {
                "exclude": "ok", 
                "record_id": "a-01-J-5558", 
                "uuid": "d82e3fc9-401a-473b-b158-6601b3cda97b"
            }, 
            {
                "exclude": "ok", 
                "record_id": "a-01-J-5559", 
                "uuid": "d1bdb466-1f8f-469d-8837-9033deddd16c"
            }, 
            {
                "exclude": "ok", 
                "record_id": "a-01-J-5560", 
                "uuid": "a4f536dd-bcda-4984-b855-5c4fb152defb"
            }, 
            {
                "exclude": "omit", 
                "record_id": "a-01-J-5561", 
                "uuid": "85a96c9a-8f82-468f-b8c8-1314a6110a25"
            }, 
            {
                "exclude": "ok", 
                "record_id": "a-01-J-5562", 
                "uuid": "d87de8c5-466b-4a3f-ac33-e5fe75e9661f"
            }, 
            {
                "exclude": "omit", 
                "record_id": "a-01-J-5563", 
                "uuid": "df453aca-0815-489a-a8ae-443aaa7c62a5"
            }, 
            {
                "exclude": "ok", 
                "record_id": "a-01-J-5564", 
                "uuid": "8e32bcd3-8d62-4a51-8216-269d7f76783e"
            }, 
            {
                "exclude": "ok", 
                "record_id": "a-01-J-5565", 
                "uuid": "2faf0cb0-1e8d-46b1-9563-feda77801e45"
            }, 
            {
                "exclude": "ok", 
                "record_id": "a-01-J-5566", 
                "uuid": "867b7c4e-f464-475d-bcd3-f78f4e379eb9"
            }, 
            {
                "exclude": "omit", 
                "record_id": "a-01-J-5567", 
                "uuid": "7aace4f8-c898-4ac4-b9a3-31a7b96effa7"
            }, 
            {
                "exclude": "ok", 
                "record_id": "a-01-J-5568", 
                "uuid": "49cff695-5786-4685-9279-6253b214a4f8"
            }, 
            {
                "exclude": "omit", 
                "record_id": "a-01-J-5569", 
                "uuid": "2ae2845f-b223-4120-8263-b540f6c440e8"
            }, 
            {
                "exclude": "omit", 
                "record_id": "a-01-J-5570", 
                "uuid": "e65ee6d6-99e2-4e52-beea-3f1177f4dc23"
            }, 
            {
                "exclude": "omit", 
                "record_id": "a-01-J-5571", 
                "uuid": "01335d4d-0b00-4488-ada8-3ea33130107f"
            }
        ], 
        "value": 1.0015633543916855
    }, 
    "H1": {
        "error": 1e-20, 
        "fit": "default", 
        "references": [], 
        "value": 1.0
    }, 
    "H2": {
        "error": 1e-20, 
        "fit": "default", 
        "references": [], 
        "value": 1.0
    }, 
    "L1": {
        "error": 1e-20, 
        "fit": "default", 
        "references": [], 
        "value": 1.0
    }, 
    "L2": {
        "error": 1e-20, 
        "fit": "default", 
        "references": [], 
        "value": 1.0
    }, 
    "reviewed": true
}