{
    "Ar36": {
        "error": 0.0004620876849776911, 
        "filter_outliers_dict": {
            "filter_outliers": true, 
            "iterations": 1, 
            "std_devs": 2
        }, 
        "fit": "Linear", 
        "value": 0.024951292583715548
    }, 
    "Ar37": {
        "error": 0.010517498311447012, 
        "filter_outliers_dict": {
            "filter_outliers": true, 
            "iterations": 1, 
            "std_devs": 2
        }, 
        "fit": "linear", 
        "value": 0.6186314223295246
    }, 
    "Ar38": {
        "error": 0.005126650283241519, 
        "filter_outliers_dict": {
            "filter_outliers": true, 
            "iterations": 1, 
            "std_devs": 2
        }, 
        "fit": "linear", 
        "value": 1.2351204941490077
    }, 
    "Ar39": {
        "error": 0.02371667391553514, 
        "filter_outliers_dict": {
            "filter_outliers": true, 
            "iterations": 1, 
            "std_devs": 2
        }, 
        "fit": "Linear", 
        "value": 97.22938771587462
    }, 
    "Ar40": {
        "error": 0.035285200812469594, 
        "filter_outliers_dict": {
            "filter_outliers": true, 
            "iterations": 1, 
            "std_devs": 2
        }, 
        "fit": "Linear", 
        "value": 483.46813551096477
    }, 
    "Ar41": {
        "error": 0.006078396656951831, 
        "filter_outliers_dict": {
            "filter_outliers": true, 
            "iterations": 1, 
            "std_devs": 2
        }, 
        "fit": "Average", 
        "value": -0.15817936138983407
    }
}