{
    "Ar36": {
        "error": 0.000304024816415897, 
        "filter_outliers_dict": {
            "filter_outliers": true, 
            "iterations": 1, 
            "std_devs": 2
        }, 
        "fit": "Linear", 
        "value": 0.011041577026694583
    }, 
    "Ar37": {
        "error": 0.012112835480345268, 
        "filter_outliers_dict": {
            "filter_outliers": true, 
            "iterations": 1, 
            "std_devs": 2
        }, 
        "fit": "linear", 
        "value": 0.43163677104042464
    }, 
    "Ar38": {
        "error": 0.00568591579389133, 
        "filter_outliers_dict": {
            "filter_outliers": true, 
            "iterations": 1, 
            "std_devs": 2
        }, 
        "fit": "linear", 
        "value": 1.2406603642939253
    }, 
    "Ar39": {
        "error": 0.019642691568522937, 
        "filter_outliers_dict": {
            "filter_outliers": true, 
            "iterations": 1, 
            "std_devs": 2
        }, 
        "fit": "Linear", 
        "value": 97.42658247638234
    }, 
    "Ar40": {
        "error": 0.042424151251116864, 
        "filter_outliers_dict": {
            "filter_outliers": true, 
            "iterations": 1, 
            "std_devs": 2
        }, 
        "fit": "Linear", 
        "value": 614.8656695755508
    }, 
    "Ar41": {
        "error": 0.005823570012794343, 
        "filter_outliers_dict": {
            "filter_outliers": true, 
            "iterations": 1, 
            "std_devs": 2
        }, 
        "fit": "Average", 
        "value": -0.13934044534424797
    }
}