{
    "Ar36": {
        "error": 0.00031745564958258517, 
        "filter_outliers_dict": {
            "filter_outliers": true, 
            "iterations": 1, 
            "std_devs": 2
        }, 
        "fit": "Linear", 
        "value": 0.015434789217420518
    }, 
    "Ar37": {
        "error": 0.009640185217039408, 
        "filter_outliers_dict": {
            "filter_outliers": true, 
            "iterations": 1, 
            "std_devs": 2
        }, 
        "fit": "linear", 
        "value": 0.6438055086274344
    }, 
    "Ar38": {
        "error": 0.004330904007176159, 
        "filter_outliers_dict": {
            "filter_outliers": true, 
            "iterations": 1, 
            "std_devs": 2
        }, 
        "fit": "linear", 
        "value": 1.6115771703570756
    }, 
    "Ar39": {
        "error": 0.022349088148925923, 
        "filter_outliers_dict": {
            "filter_outliers": true, 
            "iterations": 1, 
            "std_devs": 2
        }, 
        "fit": "Linear", 
        "value": 126.43789279811102
    }, 
    "Ar40": {
        "error": 0.054734993077008125, 
        "filter_outliers_dict": {
            "filter_outliers": true, 
            "iterations": 1, 
            "std_devs": 2
        }, 
        "fit": "Linear", 
        "value": 799.6669654224738
    }, 
    "Ar41": {
        "error": 0.004904060165098588, 
        "filter_outliers_dict": {
            "filter_outliers": true, 
            "iterations": 1, 
            "std_devs": 2
        }, 
        "fit": "Average", 
        "value": -0.13418452382464102
    }
}