{
    "Ar36": {
        "error": 0.0003427198201561414, 
        "filter_outliers_dict": {
            "filter_outliers": true, 
            "iterations": 1, 
            "std_devs": 2
        }, 
        "fit": "Linear", 
        "value": 0.012963415135467643
    }, 
    "Ar37": {
        "error": 0.010365116937806715, 
        "filter_outliers_dict": {
            "filter_outliers": true, 
            "iterations": 1, 
            "std_devs": 2
        }, 
        "fit": "linear", 
        "value": 0.051769031238263305
    }, 
    "Ar38": {
        "error": 0.004386901532322378, 
        "filter_outliers_dict": {
            "filter_outliers": true, 
            "iterations": 1, 
            "std_devs": 2
        }, 
        "fit": "linear", 
        "value": 0.16576610424105745
    }, 
    "Ar39": {
        "error": 0.014386480982187425, 
        "filter_outliers_dict": {
            "filter_outliers": true, 
            "iterations": 1, 
            "std_devs": 2
        }, 
        "fit": "Linear", 
        "value": 13.259271713852295
    }, 
    "Ar40": {
        "error": 0.07897275081429966, 
        "filter_outliers_dict": {
            "filter_outliers": true, 
            "iterations": 1, 
            "std_devs": 2
        }, 
        "fit": "Linear", 
        "value": 44.80228659685799
    }, 
    "Ar41": {
        "error": 0.004636530938149414, 
        "filter_outliers_dict": {
            "filter_outliers": true, 
            "iterations": 1, 
            "std_devs": 2
        }, 
        "fit": "Average", 
        "value": -0.18520993415337675
    }
}