{
    "Ar36": {
        "error": 0.00022744458752392224, 
        "filter_outliers_dict": {
            "filter_outliers": true, 
            "iterations": 1, 
            "std_devs": 2
        }, 
        "fit": "Linear", 
        "value": 0.005036091907135042
    }, 
    "Ar37": {
        "error": 0.010106246678757187, 
        "filter_outliers_dict": {
            "filter_outliers": true, 
            "iterations": 1, 
            "std_devs": 2
        }, 
        "fit": "linear", 
        "value": 0.15818745417937272
    }, 
    "Ar38": {
        "error": 0.004741658324348265, 
        "filter_outliers_dict": {
            "filter_outliers": true, 
            "iterations": 1, 
            "std_devs": 2
        }, 
        "fit": "linear", 
        "value": 0.07724894793117969
    }, 
    "Ar39": {
        "error": 0.012305410514301037, 
        "filter_outliers_dict": {
            "filter_outliers": true, 
            "iterations": 1, 
            "std_devs": 2
        }, 
        "fit": "Linear", 
        "value": 7.48928022421777
    }, 
    "Ar40": {
        "error": 0.011460235778872107, 
        "filter_outliers_dict": {
            "filter_outliers": true, 
            "iterations": 1, 
            "std_devs": 2
        }, 
        "fit": "Linear", 
        "value": 18.585192045841787
    }, 
    "Ar41": {
        "error": 0.005505049024674505, 
        "filter_outliers_dict": {
            "filter_outliers": true, 
            "iterations": 1, 
            "std_devs": 2
        }, 
        "fit": "Average", 
        "value": -0.18168431426443066
    }
}