{
    "Ar36": {
        "error": 0.00023541217878316926, 
        "filter_outliers_dict": {
            "filter_outliers": true, 
            "iterations": 1, 
            "std_devs": 2
        }, 
        "fit": "Linear", 
        "value": 0.007307533442497771
    }, 
    "Ar37": {
        "error": 0.011304537933672284, 
        "filter_outliers_dict": {
            "filter_outliers": true, 
            "iterations": 1, 
            "std_devs": 2
        }, 
        "fit": "linear", 
        "value": 0.16287793009853818
    }, 
    "Ar38": {
        "error": 0.004201563719364764, 
        "filter_outliers_dict": {
            "filter_outliers": true, 
            "iterations": 1, 
            "std_devs": 2
        }, 
        "fit": "linear", 
        "value": 0.1546294792092615
    }, 
    "Ar39": {
        "error": 0.01378520857533487, 
        "filter_outliers_dict": {
            "filter_outliers": true, 
            "iterations": 1, 
            "std_devs": 2
        }, 
        "fit": "Linear", 
        "value": 12.247767425800122
    }, 
    "Ar40": {
        "error": 0.013559139937427328, 
        "filter_outliers_dict": {
            "filter_outliers": true, 
            "iterations": 1, 
            "std_devs": 2
        }, 
        "fit": "Linear", 
        "value": 30.368215727464495
    }, 
    "Ar41": {
        "error": 0.005438681215402555, 
        "filter_outliers_dict": {
            "filter_outliers": true, 
            "iterations": 1, 
            "std_devs": 2
        }, 
        "fit": "Average", 
        "value": -0.1768700157130664
    }
}