{
    "AX": {
        "error": 0.006125500774852982, 
        "filter_outliers_dict": {
            "filter_outliers": true, 
            "iterations": 1, 
            "std_devs": 2
        }, 
        "fit": "average", 
        "value": -0.0749562978205326
    }, 
    "CDD": {
        "error": 2.4899329985439256e-05, 
        "filter_outliers_dict": {
            "filter_outliers": true, 
            "iterations": 1, 
            "std_devs": 10
        }, 
        "fit": "average", 
        "value": 0.00021589789675660346
    }, 
    "H1": {
        "error": 0.005740262435958784, 
        "filter_outliers_dict": {
            "filter_outliers": true, 
            "iterations": 1, 
            "std_devs": 2
        }, 
        "fit": "average", 
        "value": 0.16175072086830228
    }, 
    "H2": {
        "error": 0.007946232793099747, 
        "filter_outliers_dict": {
            "filter_outliers": true, 
            "iterations": 1, 
            "std_devs": 2
        }, 
        "fit": "average", 
        "value": -0.21167879045626517
    }, 
    "L1": {
        "error": 0.0023896041380758264, 
        "filter_outliers_dict": {
            "filter_outliers": true, 
            "iterations": 1, 
            "std_devs": 2
        }, 
        "fit": "average", 
        "value": -0.030670938776751658
    }, 
    "L2": {
        "error": 0.006029368534213495, 
        "filter_outliers_dict": {
            "filter_outliers": true, 
            "iterations": 1, 
            "std_devs": 2
        }, 
        "fit": "average", 
        "value": -0.023962285179863457
    }
}