{
    "AX": {
        "error": 0.005888945989553465, 
        "filter_outliers_dict": {
            "filter_outliers": true, 
            "iterations": 1, 
            "std_devs": 2
        }, 
        "fit": "average", 
        "value": -0.06660321457800925
    }, 
    "CDD": {
        "error": 6.295219865947779e-06, 
        "filter_outliers_dict": {
            "filter_outliers": true, 
            "iterations": 1, 
            "std_devs": 10
        }, 
        "fit": "average", 
        "value": 1.7573084358594918e-05
    }, 
    "H1": {
        "error": 0.004605668150112435, 
        "filter_outliers_dict": {
            "filter_outliers": true, 
            "iterations": 1, 
            "std_devs": 2
        }, 
        "fit": "average", 
        "value": 0.10190793202517388
    }, 
    "H2": {
        "error": 0.007243633647656241, 
        "filter_outliers_dict": {
            "filter_outliers": true, 
            "iterations": 1, 
            "std_devs": 2
        }, 
        "fit": "average", 
        "value": -0.1885293072462743
    }, 
    "L1": {
        "error": 0.002636561372410814, 
        "filter_outliers_dict": {
            "filter_outliers": true, 
            "iterations": 1, 
            "std_devs": 2
        }, 
        "fit": "average", 
        "value": -0.033599715249305606
    }, 
    "L2": {
        "error": 0.008091430056077868, 
        "filter_outliers_dict": {
            "filter_outliers": true, 
            "iterations": 1, 
            "std_devs": 2
        }, 
        "fit": "average", 
        "value": -0.030319719515442774
    }
}