{
    "AX": {
        "error": 0.006722176788932888, 
        "filter_outliers_dict": {
            "filter_outliers": true, 
            "iterations": 1, 
            "std_devs": 2
        }, 
        "fit": "average", 
        "value": -0.061060100628260214
    }, 
    "CDD": {
        "error": 5.419887785704298e-06, 
        "filter_outliers_dict": {
            "filter_outliers": true, 
            "iterations": 1, 
            "std_devs": 10
        }, 
        "fit": "average", 
        "value": 1.2552203113282084e-05
    }, 
    "H1": {
        "error": 0.005262974353823054, 
        "filter_outliers_dict": {
            "filter_outliers": true, 
            "iterations": 1, 
            "std_devs": 2
        }, 
        "fit": "average", 
        "value": 0.10105901163254427
    }, 
    "H2": {
        "error": 0.007413183769177916, 
        "filter_outliers_dict": {
            "filter_outliers": true, 
            "iterations": 1, 
            "std_devs": 2
        }, 
        "fit": "average", 
        "value": -0.20306342303854447
    }, 
    "L1": {
        "error": 0.002237496774137351, 
        "filter_outliers_dict": {
            "filter_outliers": true, 
            "iterations": 1, 
            "std_devs": 2
        }, 
        "fit": "average", 
        "value": -0.03070036507601519
    }, 
    "L2": {
        "error": 0.0060148941664370905, 
        "filter_outliers_dict": {
            "filter_outliers": true, 
            "iterations": 1, 
            "std_devs": 2
        }, 
        "fit": "average", 
        "value": -0.012065889804982709
    }
}