{
    "AX": {
        "error": 0.007496536189850262, 
        "filter_outliers_dict": {
            "filter_outliers": true, 
            "iterations": 1, 
            "std_devs": 2
        }, 
        "fit": "average", 
        "value": 0.037524530705846625
    }, 
    "CDD": {
        "error": 1.310677596231684e-05, 
        "filter_outliers_dict": {
            "filter_outliers": true, 
            "iterations": 1, 
            "std_devs": 10
        }, 
        "fit": "average", 
        "value": 7.25598630300096e-05
    }, 
    "H1": {
        "error": 0.004876820600356312, 
        "filter_outliers_dict": {
            "filter_outliers": true, 
            "iterations": 1, 
            "std_devs": 2
        }, 
        "fit": "average", 
        "value": -0.02890560831076407
    }, 
    "H2": {
        "error": 0.007194740002774178, 
        "filter_outliers_dict": {
            "filter_outliers": true, 
            "iterations": 1, 
            "std_devs": 2
        }, 
        "fit": "average", 
        "value": 0.07588474649028452
    }, 
    "L1": {
        "error": 0.003733099508468882, 
        "filter_outliers_dict": {
            "filter_outliers": true, 
            "iterations": 1, 
            "std_devs": 2
        }, 
        "fit": "average", 
        "value": 0.0007161475891264541
    }, 
    "L2": {
        "error": 0.007121877014624935, 
        "filter_outliers_dict": {
            "filter_outliers": true, 
            "iterations": 1, 
            "std_devs": 2
        }, 
        "fit": "average", 
        "value": 0.13653550962207864
    }
}