{
    "AX": {
        "error": 0.007234341561240567, 
        "filter_outliers_dict": {
            "filter_outliers": true, 
            "iterations": 1, 
            "std_devs": 2
        }, 
        "fit": "average", 
        "value": 0.05116681527021758
    }, 
    "CDD": {
        "error": 9.766800024224583e-06, 
        "filter_outliers_dict": {
            "filter_outliers": true, 
            "iterations": 1, 
            "std_devs": 10
        }, 
        "fit": "average", 
        "value": 4.753922046599037e-05
    }, 
    "H1": {
        "error": 0.004017522653366071, 
        "filter_outliers_dict": {
            "filter_outliers": true, 
            "iterations": 1, 
            "std_devs": 2
        }, 
        "fit": "average", 
        "value": -0.03918746879921867
    }, 
    "H2": {
        "error": 0.005776512703753134, 
        "filter_outliers_dict": {
            "filter_outliers": true, 
            "iterations": 1, 
            "std_devs": 2
        }, 
        "fit": "average", 
        "value": 0.11409530797521412
    }, 
    "L1": {
        "error": 0.002497353809626229, 
        "filter_outliers_dict": {
            "filter_outliers": true, 
            "iterations": 1, 
            "std_devs": 2
        }, 
        "fit": "average", 
        "value": 0.0015117409673556627
    }, 
    "L2": {
        "error": 0.004873590258490046, 
        "filter_outliers_dict": {
            "filter_outliers": true, 
            "iterations": 1, 
            "std_devs": 2
        }, 
        "fit": "average", 
        "value": 0.1322252722020317
    }
}