{
    "Ar36": {
        "error": 0.0009558562526075292, 
        "filter_outliers_dict": {
            "filter_outliers": true, 
            "iterations": 1, 
            "std_devs": 2
        }, 
        "fit": "Linear", 
        "value": 0.16134299612606284
    }, 
    "Ar37": {
        "error": 0.008818528199910724, 
        "filter_outliers_dict": {
            "filter_outliers": true, 
            "iterations": 1, 
            "std_devs": 2
        }, 
        "fit": "linear", 
        "value": 2.284447172055387
    }, 
    "Ar38": {
        "error": 0.007593336219419765, 
        "filter_outliers_dict": {
            "filter_outliers": true, 
            "iterations": 1, 
            "std_devs": 2
        }, 
        "fit": "linear", 
        "value": 6.256541010068112
    }, 
    "Ar39": {
        "error": 0.04859535061941233, 
        "filter_outliers_dict": {
            "filter_outliers": true, 
            "iterations": 1, 
            "std_devs": 2
        }, 
        "fit": "Linear", 
        "value": 489.42677073974687
    }, 
    "Ar40": {
        "error": 0.18139433585331144, 
        "filter_outliers_dict": {
            "filter_outliers": true, 
            "iterations": 1, 
            "std_devs": 2
        }, 
        "fit": "Linear", 
        "value": 2531.5516156986378
    }, 
    "Ar41": {
        "error": 0.003820972427366595, 
        "filter_outliers_dict": {
            "filter_outliers": true, 
            "iterations": 1, 
            "std_devs": 2
        }, 
        "fit": "Average", 
        "value": 0.1700327320272896
    }
}