{
    "Ar36": {
        "error": 0.0004032360038270742, 
        "filter_outliers_dict": {
            "filter_outliers": true, 
            "iterations": 1, 
            "std_devs": 2
        }, 
        "fit": "Linear", 
        "value": 0.025290672118394423
    }, 
    "Ar37": {
        "error": 0.011345276742618324, 
        "filter_outliers_dict": {
            "filter_outliers": true, 
            "iterations": 1, 
            "std_devs": 2
        }, 
        "fit": "linear", 
        "value": 1.382260510039864
    }, 
    "Ar38": {
        "error": 0.0055631738510369694, 
        "filter_outliers_dict": {
            "filter_outliers": true, 
            "iterations": 1, 
            "std_devs": 2
        }, 
        "fit": "linear", 
        "value": 4.780349317170755
    }, 
    "Ar39": {
        "error": 0.037525700864649354, 
        "filter_outliers_dict": {
            "filter_outliers": true, 
            "iterations": 1, 
            "std_devs": 2
        }, 
        "fit": "Linear", 
        "value": 373.627297443193
    }, 
    "Ar40": {
        "error": 0.09536348043248173, 
        "filter_outliers_dict": {
            "filter_outliers": true, 
            "iterations": 1, 
            "std_devs": 2
        }, 
        "fit": "Linear", 
        "value": 1523.364847529265
    }, 
    "Ar41": {
        "error": 0.004512171387876221, 
        "filter_outliers_dict": {
            "filter_outliers": true, 
            "iterations": 1, 
            "std_devs": 2
        }, 
        "fit": "Average", 
        "value": 0.13745696190604526
    }
}