{
    "Ar36": {
        "error": 0.0004569716219136423, 
        "filter_outliers_dict": {
            "filter_outliers": true, 
            "iterations": 1, 
            "std_devs": 2
        }, 
        "fit": "Linear", 
        "value": 0.034123626720748396
    }, 
    "Ar37": {
        "error": 0.009280688671265226, 
        "filter_outliers_dict": {
            "filter_outliers": true, 
            "iterations": 1, 
            "std_devs": 2
        }, 
        "fit": "linear", 
        "value": 2.2193523907194272
    }, 
    "Ar38": {
        "error": 0.003970751211230892, 
        "filter_outliers_dict": {
            "filter_outliers": true, 
            "iterations": 1, 
            "std_devs": 2
        }, 
        "fit": "linear", 
        "value": 1.5256221895699802
    }, 
    "Ar39": {
        "error": 0.0219786067420883, 
        "filter_outliers_dict": {
            "filter_outliers": true, 
            "iterations": 1, 
            "std_devs": 2
        }, 
        "fit": "Linear", 
        "value": 117.74507883087722
    }, 
    "Ar40": {
        "error": 0.029455471862988535, 
        "filter_outliers_dict": {
            "filter_outliers": true, 
            "iterations": 1, 
            "std_devs": 2
        }, 
        "fit": "Linear", 
        "value": 280.49628438580226
    }, 
    "Ar41": {
        "error": 0.004004556933611377, 
        "filter_outliers_dict": {
            "filter_outliers": true, 
            "iterations": 1, 
            "std_devs": 2
        }, 
        "fit": "Average", 
        "value": 0.09165734184447535
    }
}