{
    "Ar36": {
        "error": 0.0002992157183764604,
        "error_type": "SEM",
        "filter_outliers_dict": {
            "filter_outliers": true,
            "iterations": 1,
            "std_devs": 3,
            "use_iqr_filtering": false,
            "use_standard_deviation_filtering": false
        },
        "fit": "linear",
        "fn": 399,
        "include_baseline_error": true,
        "n": 400,
        "outlier_excluded": [
            206
        ],
        "reviewed": true,
        "user_excluded": [],
        "value": 0.04751994930200212
    },
    "Ar37": {
        "error": 0.012532828515861034,
        "error_type": "SEM",
        "filter_outliers_dict": {
            "filter_outliers": true,
            "iterations": 1,
            "std_devs": 3,
            "use_iqr_filtering": false,
            "use_standard_deviation_filtering": false
        },
        "fit": "linear",
        "fn": 400,
        "include_baseline_error": true,
        "n": 400,
        "outlier_excluded": [],
        "reviewed": true,
        "user_excluded": [],
        "value": -0.11322614801370379
    },
    "Ar38": {
        "error": 0.013255824060548283,
        "error_type": "SEM",
        "filter_outliers_dict": {
            "filter_outliers": true,
            "iterations": 1,
            "std_devs": 3,
            "use_iqr_filtering": false,
            "use_standard_deviation_filtering": false
        },
        "fit": "linear",
        "fn": 399,
        "include_baseline_error": true,
        "n": 400,
        "outlier_excluded": [
            126
        ],
        "reviewed": true,
        "user_excluded": [],
        "value": -0.8607418975846866
    },
    "Ar39": {
        "error": 0.015387678652758637,
        "error_type": "SEM",
        "filter_outliers_dict": {
            "filter_outliers": true,
            "iterations": 1,
            "std_devs": 3,
            "use_iqr_filtering": false,
            "use_standard_deviation_filtering": false
        },
        "fit": "linear",
        "fn": 396,
        "include_baseline_error": true,
        "n": 400,
        "outlier_excluded": [
            0,
            1,
            2,
            61
        ],
        "reviewed": true,
        "user_excluded": [],
        "value": 54.35720719649538
    },
    "Ar40": {
        "error": 0.05560874215657076,
        "error_type": "SEM",
        "filter_outliers_dict": {
            "filter_outliers": true,
            "iterations": 1,
            "std_devs": 3,
            "use_iqr_filtering": false,
            "use_standard_deviation_filtering": false
        },
        "fit": "parabolic",
        "fn": 397,
        "include_baseline_error": true,
        "n": 400,
        "outlier_excluded": [
            0,
            1,
            2
        ],
        "reviewed": true,
        "user_excluded": [],
        "value": 537.2731055909708
    }
}