{
    "Ar36": {
        "error": 0.0007867961770674806, 
        "filter_outliers_dict": {
            "filter_outliers": true, 
            "iterations": 1, 
            "std_devs": 2
        }, 
        "fit": "Parabolic", 
        "value": 0.13831129020692162
    }, 
    "Ar37": {
        "error": 0.012066275354486995, 
        "filter_outliers_dict": {
            "filter_outliers": true, 
            "iterations": 1, 
            "std_devs": 2
        }, 
        "fit": "linear", 
        "value": 0.21534780570569279
    }, 
    "Ar38": {
        "error": 0.012796384073929365, 
        "filter_outliers_dict": {
            "filter_outliers": true, 
            "iterations": 1, 
            "std_devs": 2
        }, 
        "fit": "linear", 
        "value": -1.0032399346490377
    }, 
    "Ar39": {
        "error": 0.027318161847910888, 
        "filter_outliers_dict": {
            "filter_outliers": true, 
            "iterations": 1, 
            "std_devs": 2
        }, 
        "fit": "Parabolic", 
        "value": 43.87114063007209
    }, 
    "Ar40": {
        "error": 0.056917327640389155, 
        "filter_outliers_dict": {
            "filter_outliers": true, 
            "iterations": 1, 
            "std_devs": 2
        }, 
        "fit": "Parabolic", 
        "value": 581.6979841847262
    }
}