{
    "Ar36": {
        "error": 0.00021281331115048047, 
        "filter_outliers_dict": {
            "filter_outliers": true, 
            "iterations": 1, 
            "std_devs": 2
        }, 
        "fit": "Parabolic", 
        "value": 0.00573691237467094
    }, 
    "Ar37": {
        "error": 0.011381326324367358, 
        "filter_outliers_dict": {
            "filter_outliers": true, 
            "iterations": 1, 
            "std_devs": 2
        }, 
        "fit": "linear", 
        "value": 1.2685026299612872
    }, 
    "Ar38": {
        "error": 0.02659577857515679, 
        "filter_outliers_dict": {
            "filter_outliers": true, 
            "iterations": 1, 
            "std_devs": 2
        }, 
        "fit": "linear", 
        "value": -0.4473185478017854
    }, 
    "Ar39": {
        "error": 0.02336977471256405, 
        "filter_outliers_dict": {
            "filter_outliers": true, 
            "iterations": 1, 
            "std_devs": 2
        }, 
        "fit": "Parabolic", 
        "value": 0.43506389882398105
    }, 
    "Ar40": {
        "error": 0.019063846480368934, 
        "filter_outliers_dict": {
            "filter_outliers": true, 
            "iterations": 1, 
            "std_devs": 2
        }, 
        "fit": "Parabolic", 
        "value": 2.5012331662967577
    }
}